{
  "db_name": "PostgreSQL",
  "query": "\n        UPDATE kb_system_settings\n           SET gating_team_slug   = COALESCE($1, gating_team_slug),\n               instance_name      = COALESCE($2, instance_name),\n               terms_version      = COALESCE($3, terms_version),\n               terms_resource_uri = COALESCE($4, terms_resource_uri),\n               updated            = now()\n         WHERE id = 1\n        RETURNING id, access_mode, gating_team_slug, terms_version,\n                  terms_resource_uri, instance_name, updated\n        ",
  "describe": {
    "columns": [
      {
        "ordinal": 0,
        "name": "id",
        "type_info": "Int4"
      },
      {
        "ordinal": 1,
        "name": "access_mode",
        "type_info": "Varchar"
      },
      {
        "ordinal": 2,
        "name": "gating_team_slug",
        "type_info": "Varchar"
      },
      {
        "ordinal": 3,
        "name": "terms_version",
        "type_info": "Varchar"
      },
      {
        "ordinal": 4,
        "name": "terms_resource_uri",
        "type_info": "Text"
      },
      {
        "ordinal": 5,
        "name": "instance_name",
        "type_info": "Varchar"
      },
      {
        "ordinal": 6,
        "name": "updated",
        "type_info": "Timestamptz"
      }
    ],
    "parameters": {
      "Left": [
        "Varchar",
        "Varchar",
        "Varchar",
        "Text"
      ]
    },
    "nullable": [
      false,
      false,
      true,
      true,
      true,
      true,
      false
    ]
  },
  "hash": "31141fd9cc99b37cb147e4cece4edbdf667492dd55b21d204d8617dd62097c98"
}
