{
  "db_name": "PostgreSQL",
  "query": "INSERT INTO kb_resource_access (resource_id, anchor_table, anchor_id, can_read, can_write, can_delete, can_grant, granted_by_profile_id) VALUES ($1,$2,$3,$4,$5,$6,$7,$8)",
  "describe": {
    "columns": [],
    "parameters": {
      "Left": [
        "Uuid",
        "Varchar",
        "Uuid",
        "Bool",
        "Bool",
        "Bool",
        "Bool",
        "Uuid"
      ]
    },
    "nullable": []
  },
  "hash": "8da79128604bfc5c0ba23080651f45c4cff91409977c1b31176f440f4882e53f"
}
